dlw/DLWSubject.py
dlw/__init__.py
dlw/web/__init__.py
dlw/web/app.py
dlw/web/dist/app.js
dlw/web/dist/codepack.js
dlw/web/dist/index.html
dlw/web/dist/assets/favicon.ico
dlw/web/dist/assets/logo_cuhs.png
dlw/web/dist/assets/css/style.css
dlw-0.0.18.dist-info/LICENSE
dlw-0.0.18.dist-info/METADATA
dlw-0.0.18.dist-info/WHEEL
dlw-0.0.18.dist-info/entry_points.txt
dlw-0.0.18.dist-info/top_level.txt
dlw-0.0.18.dist-info/RECORD
