Metadata-Version: 2.1
Name: dlw
Version: 0.0.18
Summary: Open source web app to conduct doubly labeled water study calculations.
Home-page: https://github.com/jchmyz/DoublyLabeledWater
Author: Julia Chmyz
Author-email: julia@chmyz.com
License: LICENSE.txt
Platform: UNKNOWN
License-File: LICENSE
Requires-Dist: numpy
Requires-Dist: scipy
Requires-Dist: python-csv
Requires-Dist: flask
Requires-Dist: flask-restful
